nft_price_tracker/__init__.py
nft_price_tracker/magiceden.py
nft_price_tracker/main.py
nft_price_tracker/opensea.py
nft_price_tracker-0.2.0.dist-info/METADATA
nft_price_tracker-0.2.0.dist-info/WHEEL
nft_price_tracker-0.2.0.dist-info/top_level.txt
nft_price_tracker-0.2.0.dist-info/RECORD
