Metadata-Version: 2.4
Name: nft-price-tracker
Version: 0.2.0
Summary: A package to track NFT prices across OpenSea and Magic Eden marketplaces
Home-page: https://github.com/danghuy174/nft-price-tracker
Author: danghuy174
Author-email: danghuy174@gmail.com
Classifier: Development Status :: 3 - Alpha
Classifier: Intended Audience :: Developers
Classifier: License :: OSI Approved :: MIT License
Classifier: Operating System :: OS Independent
Classifier: Programming Language :: Python :: 3
Classifier: Programming Language :: Python :: 3.7
Classifier: Programming Language :: Python :: 3.8
Classifier: Programming Language :: Python :: 3.9
Classifier: Programming Language :: Python :: 3.10
Requires-Python: >=3.7
Requires-Dist: aiohttp>=3.8.0
Requires-Dist: python-dotenv>=0.19.0
Requires-Dist: requests>=2.26.0
Dynamic: author
Dynamic: author-email
Dynamic: classifier
Dynamic: description
Dynamic: description-content-type
Dynamic: home-page
Dynamic: requires-dist
Dynamic: requires-python
Dynamic: summary
